pyption/__init__.py
pyption/option.py
pyption-1.0.0.dist-info/LICENSE
pyption-1.0.0.dist-info/METADATA
pyption-1.0.0.dist-info/WHEEL
pyption-1.0.0.dist-info/RECORD
