Metadata-Version: 2.1
Name: pyption
Version: 1.0.0
Summary: type Option, Some contains some value and Nothing contains absolutely nothing.
Home-page: https://github.com/luwqz1/telegrinder_templating
License: MIT
Keywords: python,option type,rust option,some nothing
Author: Georgy Kritov
Author-email: howluwqz1@gmail.com
Requires-Python: >=3.10,<4.0
Classifier: Intended Audience :: Developers
Classifier: Intended Audience :: Information Technology
Classifier: Intended Audience :: System Administrators
Classifier: License :: OSI Approved :: MIT License
Classifier: Programming Language :: Python :: 3
Classifier: Programming Language :: Python :: 3.10
Classifier: Programming Language :: Python :: 3.11
Classifier: Programming Language :: Python :: 3 :: Only
Classifier: Programming Language :: Python :: Implementation :: PyPy
Classifier: Topic :: Communications :: Chat
Classifier: Topic :: Internet
Classifier: Topic :: Software Development :: Libraries :: Python Modules
Requires-Dist: typing-extensions (>=4.7.1,<5.0.0)
Project-URL: Repository, https://github.com/luwqz1/telegrinder_templating
